MANIFEST.in
README.rst
setup.py
django_thvapp.egg-info/PKG-INFO
django_thvapp.egg-info/SOURCES.txt
django_thvapp.egg-info/dependency_links.txt
django_thvapp.egg-info/top_level.txt
thvapp/__init__.py
thvapp/admin.py
thvapp/apps.py
thvapp/models.py
thvapp/tests.py
thvapp/thvisual.py
thvapp/urls.py
thvapp/views.py
thvapp/migrations/__init__.py
thvapp/static/css/app.0488e5ada234d92497d8b827bbb7fdbb.css
thvapp/static/css/app.0488e5ada234d92497d8b827bbb7fdbb.css.map
thvapp/static/css/app.cbe6fc296ac3ad3b2def48853f24812b.css
thvapp/static/css/app.cbe6fc296ac3ad3b2def48853f24812b.css.map
thvapp/static/fonts/element-icons.535877f.woff
thvapp/static/fonts/element-icons.732389d.ttf
thvapp/static/js/app.000a0baab3139fb62d93.js
thvapp/static/js/app.000a0baab3139fb62d93.js.map
thvapp/static/js/app.ab1a92170a9f6aecb7e5.js
thvapp/static/js/app.ab1a92170a9f6aecb7e5.js.map
thvapp/static/js/manifest.2ae2e69a05c33dfc65f8.js
thvapp/static/js/manifest.2ae2e69a05c33dfc65f8.js.map
thvapp/static/js/vendor.1aae90a6206baf9c3bdb.js
thvapp/static/js/vendor.1aae90a6206baf9c3bdb.js.map
thvapp/templates/thvapps.html